{
    "Profile": {
        "resourceTemplates": [
            {
                "propertyTemplates": [
                    {
                        "mandatory": "false",
                        "repeatable": "true",
                        "type": "resource",
                        "valueConstraint": {
                            "valueTemplateRefs": [
                                "lc:RT:bf2:Provision:Place"
                            ]
                        },
                        "propertyURI": "http://id.loc.gov/ontologies/bibframe/place",
                        "propertyLabel": "Place"
                    },
                    {
                        "mandatory": "false",
                        "repeatable": "true",
                        "type": "resource",
                        "valueConstraint": {
                            "valueTemplateRefs": [
                                "lc:RT:bf2:Provision:Name"
                            ]
                        },
                        "propertyURI": "http://id.loc.gov/ontologies/bibframe/agent",
                        "propertyLabel": "Name"
                    },
                    {
                        "mandatory": "false",
                        "repeatable": "true",
                        "type": "literal",
                        "propertyURI": "http://id.loc.gov/ontologies/bibframe/date",
                        "propertyLabel": "Date",
                        "remark": "http://access.rdatoolkit.org/2.8.6.html"
                    },
                    {
                        "mandatory": "false",
                        "repeatable": "true",
                        "type": "resource",
                        "valueConstraint": {
                            "valueTemplateRefs": [
                                "lc:RT:bf2:Note"
                            ]
                        },
                        "propertyURI": "http://id.loc.gov/ontologies/bibframe/note",
                        "propertyLabel": "Note",
                        "remark": "http://access.rdatoolkit.org/2.17.7.html"
                    }
                ],
                "id": "lc:RT:bf2:PublicationInformation",
                "resourceURI": "http://id.loc.gov/ontologies/bibframe/Publication",
                "resourceLabel": "Publication",
                "author": "NDMSO",
                "date": "2019-06-11",
                "schema": "https://ld4p.github.io/sinopia/schemas/0.1.0/resource-template.json"
            },
            {
                "propertyTemplates": [
                    {
                        "mandatory": "false",
                        "repeatable": "true",
                        "type": "resource",
                        "valueConstraint": {
                            "valueTemplateRefs": [
                                "lc:RT:bf2:Provision:Place"
                            ]
                        },
                        "propertyURI": "http://id.loc.gov/ontologies/bibframe/place",
                        "propertyLabel": "Place"
                    },
                    {
                        "mandatory": "false",
                        "repeatable": "true",
                        "type": "resource",
                        "valueConstraint": {
                            "valueTemplateRefs": [
                                "lc:RT:bf2:Provision:Name"
                            ]
                        },
                        "propertyURI": "http://id.loc.gov/ontologies/bibframe/agent",
                        "propertyLabel": "Name"
                    },
                    {
                        "mandatory": "false",
                        "repeatable": "true",
                        "type": "literal",
                        "propertyURI": "http://id.loc.gov/ontologies/bibframe/date",
                        "propertyLabel": "Date",
                        "remark": "http://access.rdatoolkit.org/2.9.6.html"
                    },
                    {
                        "mandatory": "false",
                        "repeatable": "true",
                        "type": "resource",
                        "valueConstraint": {
                            "valueTemplateRefs": [
                                "lc:RT:bf2:Note"
                            ]
                        },
                        "propertyURI": "http://id.loc.gov/ontologies/bibframe/note",
                        "propertyLabel": "Statement of Function",
                        "remark": "http://access.rdatoolkit.org/2.9.4.4.html"
                    },
                    {
                        "mandatory": "false",
                        "repeatable": "true",
                        "type": "resource",
                        "valueConstraint": {
                            "valueTemplateRefs": [
                                "lc:RT:bf2:Note"
                            ]
                        },
                        "propertyURI": "http://id.loc.gov/ontologies/bibframe/note",
                        "propertyLabel": "Note",
                        "remark": "http://access.rdatoolkit.org/2.17.8.html"
                    }
                ],
                "resourceLabel": "Distribution",
                "id": "lc:RT:bf2:DistributionInformation",
                "resourceURI": "http://id.loc.gov/ontologies/bibframe/Distribution",
                "author": "NDMSO",
                "date": "2019-06-11",
                "schema": "https://ld4p.github.io/sinopia/schemas/0.1.0/resource-template.json"
            },
            {
                "propertyTemplates": [
                    {
                        "mandatory": "false",
                        "repeatable": "true",
                        "type": "resource",
                        "valueConstraint": {
                            "valueTemplateRefs": [
                                "lc:RT:bf2:Provision:Place"
                            ]
                        },
                        "propertyURI": "http://id.loc.gov/ontologies/bibframe/place",
                        "propertyLabel": "Place"
                    },
                    {
                        "mandatory": "false",
                        "repeatable": "true",
                        "type": "resource",
                        "valueConstraint": {
                            "valueTemplateRefs": [
                                "lc:RT:bf2:Provision:Name"
                            ]
                        },
                        "propertyURI": "http://id.loc.gov/ontologies/bibframe/agent",
                        "propertyLabel": "Name"
                    },
                    {
                        "mandatory": "false",
                        "repeatable": "true",
                        "type": "literal",
                        "propertyURI": "http://id.loc.gov/ontologies/bibframe/date",
                        "propertyLabel": "Date",
                        "remark": "http://access.rdatoolkit.org/2.10.6.html"
                    },
                    {
                        "mandatory": "false",
                        "repeatable": "true",
                        "type": "resource",
                        "valueConstraint": {
                            "valueTemplateRefs": [
                                "lc:RT:bf2:Note"
                            ]
                        },
                        "propertyURI": "http://id.loc.gov/ontologies/bibframe/note",
                        "propertyLabel": "Note",
                        "remark": "http://access.rdatoolkit.org/2.17.9.html"
                    }
                ],
                "id": "lc:RT:bf2:ManufactureInformation",
                "resourceLabel": "Manufacture",
                "resourceURI": "http://id.loc.gov/ontologies/bibframe/Manufacture",
                "author": "NDMSO",
                "date": "2019-06-11",
                "schema": "https://ld4p.github.io/sinopia/schemas/0.1.0/resource-template.json"
            },
            {
                "propertyTemplates": [
                    {
                        "mandatory": "false",
                        "repeatable": "true",
                        "type": "lookup",
                        "valueConstraint": {
                            "useValuesFrom": [
                                "http://id.loc.gov/vocabulary/countries"
                            ],
                            "valueDataType": {
                                "dataTypeURI": "http://id.loc.gov/ontologies/bibframe/Place"
                            }
                        },
                        "propertyURI": "http://id.loc.gov/ontologies/bflc/target",
                        "propertyLabel": "Search Place",
                        "remark": "http://access.rdatoolkit.org/2.10.2.html"
                    }
                ],
                "id": "lc:RT:bf2:Provision:Place",
                "resourceURI": "http://id.loc.gov/ontologies/bibframe/Place",
                "resourceLabel": "Place",
                "author": "NDMSO",
                "date": "2019-06-11",
                "schema": "https://ld4p.github.io/sinopia/schemas/0.1.0/resource-template.json"
            },
            {
                "propertyTemplates": [
                    {
                        "mandatory": "false",
                        "repeatable": "true",
                        "type": "lookup",
                        "valueConstraint": {
                            "useValuesFrom": [
                                "http://id.loc.gov/entities/providers"
                            ],
                            "valueDataType": {
                                "dataTypeURI": "http://id.loc.gov/ontologies/bibframe/Agent"
                            }
                        },
                        "propertyURI": "http://id.loc.gov/ontologies/bflc/target",
                        "propertyLabel": "Search Name",
                        "remark": "http://access.rdatoolkit.org/2.8.4.html"
                    },
                    {
                        "mandatory": "false",
                        "repeatable": "true",
                        "type": "literal",
                        "propertyURI": "http://www.w3.org/2000/01/rdf-schema#label",
                        "propertyLabel": "Record Name (if it does not appear above)"
                    }
                ],
                "id": "lc:RT:bf2:Provision:Name",
                "resourceURI": "http://id.loc.gov/ontologies/bibframe/Agent",
                "resourceLabel": "Name",
                "author": "NDMSO",
                "date": "2019-06-11",
                "schema": "https://ld4p.github.io/sinopia/schemas/0.1.0/resource-template.json"
            },
            {
                "propertyTemplates": [
                    {
                        "mandatory": "false",
                        "repeatable": "true",
                        "type": "resource",
                        "valueConstraint": {
                            "valueTemplateRefs": [
                                "lc:RT:bf2:Provision:Place"
                            ]
                        },
                        "propertyURI": "http://id.loc.gov/ontologies/bibframe/place",
                        "propertyLabel": "Place"
                    },
                    {
                        "mandatory": "false",
                        "repeatable": "true",
                        "type": "resource",
                        "valueConstraint": {
                            "valueTemplateRefs": [
                                "lc:RT:bf2:Provision:Name"
                            ]
                        },
                        "propertyURI": "http://id.loc.gov/ontologies/bibframe/agent",
                        "propertyLabel": "Name",
                        "remark": "Used with Unspecified"
                    },
                    {
                        "mandatory": "false",
                        "repeatable": "true",
                        "type": "literal",
                        "propertyURI": "http://id.loc.gov/ontologies/bibframe/date",
                        "propertyLabel": "Date"
                    },
                    {
                        "mandatory": "false",
                        "repeatable": "true",
                        "type": "resource",
                        "valueConstraint": {
                            "valueTemplateRefs": [
                                "lc:RT:bf2:Note"
                            ]
                        },
                        "propertyURI": "http://id.loc.gov/ontologies/bibframe/note",
                        "propertyLabel": "Note"
                    }
                ],
                "id": "lc:RT:bf2:ProductionInformation",
                "resourceURI": "http://id.loc.gov/ontologies/bibframe/Production",
                "resourceLabel": "Production",
                "author": "NDMSO",
                "date": "2019-06-11",
                "schema": "https://ld4p.github.io/sinopia/schemas/0.1.0/resource-template.json"
            }
        ],
        "id": "lc:profile:bf2:PublicationDistributionManufactureInformation",
        "title": "BIBFRAME 2.0 Publication, Distribution, Manufacturer Activity",
        "description": "Publication, Distribution, Manufacture Activity",
        "date": "2017-06-02",
        "author": "NDMSO",
        "schema": "https://ld4p.github.io/sinopia/schemas/0.1.0/profile.json"
    }
}